helloga/__init__.py
helloga/crossover.py
helloga/environment.py
helloga/fitness.py
helloga/individual.py
helloga/selector.py
tests/run_local.py
tests/test01.py
hello_genetic_algorithm-1.0.4.dist-info/LICENSE
hello_genetic_algorithm-1.0.4.dist-info/METADATA
hello_genetic_algorithm-1.0.4.dist-info/WHEEL
hello_genetic_algorithm-1.0.4.dist-info/top_level.txt
hello_genetic_algorithm-1.0.4.dist-info/RECORD
